calc_facil/__init__.py
calc_facil/calculadora.py
calc_facil/cli.py
calc_facil-1.0.0.dist-info/licenses/LICENSE
tests/__init__.py
tests/test_calculadora.py
calc_facil-1.0.0.dist-info/METADATA
calc_facil-1.0.0.dist-info/WHEEL
calc_facil-1.0.0.dist-info/entry_points.txt
calc_facil-1.0.0.dist-info/top_level.txt
calc_facil-1.0.0.dist-info/RECORD
