Metadata-Version: 2.4
Name: calc-facil
Version: 1.0.0
Summary: Uma calculadora simples para operações básicas
Home-page: https://github.com/luizelias8/calc-facil
Author: Luiz Elias
Author-email: luizelias8@gmail.com
Classifier: Topic :: Education
Classifier: Natural Language :: Portuguese (Brazilian)
Classifier: Development Status :: 5 - Production/Stable
Requires-Python: >=3.6
License-File: LICENSE
Dynamic: author
Dynamic: author-email
Dynamic: classifier
Dynamic: description
Dynamic: description-content-type
Dynamic: home-page
Dynamic: license-file
Dynamic: requires-python
Dynamic: summary
